baostockhelloworld/__init__.py
baostockhelloworld/util/__init__.py
baostockhelloworld/util/helloworldutil.py
baostockhelloworld-0.0.4.dist-info/METADATA
baostockhelloworld-0.0.4.dist-info/WHEEL
baostockhelloworld-0.0.4.dist-info/top_level.txt
baostockhelloworld-0.0.4.dist-info/RECORD
